simpler_timer/__init__.py
simpler_timer/timer.py
simpler_timer-0.0.2.dist-info/LICENSE
simpler_timer-0.0.2.dist-info/METADATA
simpler_timer-0.0.2.dist-info/WHEEL
simpler_timer-0.0.2.dist-info/entry_points.txt
simpler_timer-0.0.2.dist-info/top_level.txt
simpler_timer-0.0.2.dist-info/RECORD
