Metadata-Version: 2.1
Name: simpler_timer
Version: 0.0.2
Summary: ⏱️ A simple interactive-first timer for all your Python timekeeping needs
Author-email: Prince Ravi Leow <princeravileow@outlook.com>
License: GNU GENERAL PUBLIC LICENSE
Project-URL: Homepage, https://github.com/prince-ravi-leow/simpler_timer
Classifier: License :: OSI Approved :: GNU General Public License v2 (GPLv2)
Classifier: Programming Language :: Python
Classifier: Programming Language :: Python :: 3
Requires-Python: >=3.10
License-File: LICENSE
